{
  "sections": {
    "sticky-product-bar": {
      "type": "sticky-product-bar",
      "blocks": {
        "588d25af-4d47-43ac-9697-b98aa2f65719": {
          "type": "tab",
          "disabled": true,
          "settings": {
            "tab_title": "Overview",
            "tab_id": "product_information",
            "section_class": ""
          }
        },
        "3d20233b-8e37-486d-9595-9ce729f7d3b4": {
          "type": "tab",
          "disabled": true,
          "settings": {
            "tab_title": "FAQ",
            "tab_id": "faq",
            "section_class": ""
          }
        },
        "f83a23eb-3aae-4976-bd5a-7c20d5a41c38": {
          "type": "tab",
          "disabled": true,
          "settings": {
            "tab_title": "Reviews",
            "tab_id": "section-reviews",
            "section_class": ""
          }
        }
      },
      "block_order": [
        "588d25af-4d47-43ac-9697-b98aa2f65719",
        "3d20233b-8e37-486d-9595-9ce729f7d3b4",
        "f83a23eb-3aae-4976-bd5a-7c20d5a41c38"
      ],
      "settings": {
        "enabled": true,
        "enabled_tabs": false
      }
    },
    "main": {
      "type": "product-template",
      "blocks": {
        "11795adc-1afa-4833-a193-258f495901ef": {
          "type": "sku_block",
          "disabled": true,
          "settings": {
          }
        },
        "75a9b1b6-630e-4615-99ce-f30bbec6ea5e": {
          "type": "product_title",
          "settings": {
          }
        },
        "59b9a8d1-5bd8-4ed8-92e9-5854a801f774": {
          "type": "rating",
          "disabled": true,
          "settings": {
          }
        },
        "0471109f-c130-454e-a9ba-c56412cc11f3": {
          "type": "product_vendor",
          "disabled": true,
          "settings": {
          }
        },
        "220d69e9-8c2a-43b9-9363-ffbe33aba185": {
          "type": "product_price",
          "settings": {
          }
        },
        "d25a0285-4fb4-422d-b95b-ab67446120ad": {
          "type": "product_description",
          "settings": {
            "desc_display": "default"
          }
        },
        "919f9cdd-6184-4311-b675-742931504318": {
          "type": "coupon_block",
          "settings": {
            "image": "shopify:\/\/shop_images\/Component_2_1.png",
            "discount_off_text": "{{ product.metafields.custom.discount_off_text.value }}",
            "code": "{{ product.metafields.custom.discount_code.value }}",
            "show_copy_code_btn": true
          }
        },
        "b3ed0838-9ce6-4da4-a82b-0e9de5caa879": {
          "type": "product_options_block",
          "settings": {
            "show_product_swatches": true,
            "use_variant_image_for_swatches": true,
            "button_content": ""
          }
        },
        "0ddb7349-1bf6-4352-af41-583159a4e2fe": {
          "type": "quantity_block",
          "settings": {
          }
        },
        "1483c7ac-4a29-41ae-86f6-1e034c3b23c0": {
          "type": "accessories_section",
          "settings": {
            "title": "Accessories",
            "metafield": "accessories"
          }
        },
        "8e2ecb36-9fd8-4b5d-8561-c11f4d549609": {
          "type": "product_buttons",
          "settings": {
            "enable_payment_button": false,
            "show_custom_icons": true,
            "custom_payment_logo_1_svg": "",
            "custom_payment_logo_2_svg": "",
            "custom_payment_logo_3_svg": "",
            "custom_payment_logo_4_svg": "",
            "custom_payment_logo_5_svg": "",
            "custom_payment_logo_6_svg": "",
            "custom_payment_logo_7_svg": "",
            "custom_payment_logo_8_svg": "",
            "custom_payment_logo_9_svg": "",
            "custom_payment_logo_10_svg": "",
            "custom_payment_logo_11_svg": "",
            "custom_payment_logo_12_svg": "",
            "custom_payment_logo_13_svg": "",
            "custom_payment_logo_14_svg": "",
            "custom_payment_logo_15_svg": ""
          }
        },
        "a6857d85-dbb6-41d1-9501-c01cf5bbe11f": {
          "type": "back_in_stock",
          "disabled": true,
          "settings": {
          }
        }
      },
      "block_order": [
        "11795adc-1afa-4833-a193-258f495901ef",
        "75a9b1b6-630e-4615-99ce-f30bbec6ea5e",
        "59b9a8d1-5bd8-4ed8-92e9-5854a801f774",
        "0471109f-c130-454e-a9ba-c56412cc11f3",
        "220d69e9-8c2a-43b9-9363-ffbe33aba185",
        "d25a0285-4fb4-422d-b95b-ab67446120ad",
        "919f9cdd-6184-4311-b675-742931504318",
        "b3ed0838-9ce6-4da4-a82b-0e9de5caa879",
        "0ddb7349-1bf6-4352-af41-583159a4e2fe",
        "1483c7ac-4a29-41ae-86f6-1e034c3b23c0",
        "8e2ecb36-9fd8-4b5d-8561-c11f4d549609",
        "a6857d85-dbb6-41d1-9501-c01cf5bbe11f"
      ],
      "settings": {
        "section_id": "",
        "show_breadcrumbs": false,
        "show_pick_an_option": false,
        "enable_linked_options": false,
        "enabled_mobile_sticky_btns": true,
        "media_size": "medium",
        "enable_image_zoom": true,
        "enable_video_looping": true,
        "thumbnails_type": "grid",
        "support_email": "",
        "support_text": "",
        "feature_1_show": false,
        "feature_1_title": "Fast & Free Shipping",
        "feature_1_content": "",
        "feature_2_show": false,
        "feature_2_title": "Warranty Protection",
        "feature_2_content": "",
        "feature_3_show": false,
        "feature_3_title": "Secure Payments",
        "feature_3_content": "",
        "feature_4_show": false,
        "feature_4_title": "Multi-channel Support",
        "feature_4_content": ""
      }
    },
    "product-recommendations": {
      "type": "product-recommendations",
      "disabled": true,
      "settings": {
        "show_product_recommendations": true,
        "grid_mobile": "2",
        "heading": "You may also like",
        "show_vendor": false
      }
    },
    "f3e56056-c27e-472e-b3ee-3a70d6306c68": {
      "type": "pdp-video",
      "settings": {
        "section_id": "",
        "text_alignment": "center",
        "title": "",
        "subtitle": "",
        "content": "<p>Eleva al máximo la capacidad - Gracias a su diseño ampliable, se puede triplicar la capacidad, de 2 kWh a 6 kWh. <\/p>",
        "button_link": "",
        "button_text": "Learn More",
        "media_type": "image",
        "image": "shopify:\/\/shop_images\/web-Expandable_capacity.png",
        "mobile_image": "shopify:\/\/shop_images\/M-Expandable_capacity.png",
        "video_type": "youtube",
        "video_url": "",
        "mp4_video_url": "",
        "mp4_video_url_m": "",
        "autoplay_video": true,
        "button_2_link": "",
        "button_2_text": "Learn More"
      }
    },
    "0fa0c5cf-3f3f-4a49-8697-c4e2c14793fa": {
      "type": "pdp-video",
      "settings": {
        "section_id": "",
        "text_alignment": "center",
        "title": "",
        "subtitle": "",
        "content": "<p>Suministra energía a tus electrodomésticos esenciales como tu frigorífico durante un máximo de 42 horas¹<\/p><p>¹Datos basados en una capacidad de 6 KWh con un frigorífico de 120 W.<\/p>",
        "button_link": "",
        "button_text": "Learn More",
        "media_type": "image",
        "image": "shopify:\/\/shop_images\/web-Triple_the_power.png",
        "mobile_image": "shopify:\/\/shop_images\/M-Triple_the_power.png",
        "video_type": "youtube",
        "video_url": "",
        "mp4_video_url": "",
        "mp4_video_url_m": "",
        "autoplay_video": true,
        "button_2_link": "",
        "button_2_text": "Learn More"
      }
    },
    "c2d6654e-c56d-4556-8857-709667908743": {
      "type": "pdp-specs",
      "blocks": {
        "3d0793c4-e505-4afc-8f59-75b81df8f0f7": {
          "type": "contents",
          "settings": {
            "title": "Capacidad",
            "content": "<p>2048 Wh<\/p>"
          }
        },
        "afbf26f2-d811-42b6-8440-3a4487013c3f": {
          "type": "contents",
          "settings": {
            "title": "Puerto de entrada",
            "content": "<p>51,2 V, 2000 W máx.<\/p>"
          }
        },
        "29870530-ec9f-4290-853a-0f44c74f270e": {
          "type": "contents",
          "settings": {
            "title": "Puerto de salida",
            "content": "<p>51,2 V, 3200 W máx.<\/p>"
          }
        },
        "19377af7-ebea-42a5-914c-c1cd31d8e1ea": {
          "type": "contents",
          "settings": {
            "title": "Batería",
            "content": "<p>Química LFP, 3000 ciclos a una capacidad de más del 80 %<\/p>"
          }
        },
        "26e9c21f-90cc-4504-8415-ec2795cc27bc": {
          "type": "contents",
          "settings": {
            "title": "Dimensiones",
            "content": "<p>464 × 235 × 283 mm<\/p>"
          }
        },
        "aedd994c-83a4-47e7-912a-11067e096dff": {
          "type": "contents",
          "settings": {
            "title": "Peso",
            "content": "<p>19 kg <\/p>"
          }
        },
        "c4d514e9-ce85-4c2a-a69d-d7dfb16f8748": {
          "type": "contents",
          "settings": {
            "title": "Contenido de la caja",
            "content": "<p>Batería adicional Inteligente DELTA 2 Max<\/p><p>Cable de Batería adicional <\/p><p>Manual del usuario Tarjeta de garantía<\/p>"
          }
        },
        "bdaee37a-1d07-4d2d-8003-1c0738a60517": {
          "type": "contents",
          "settings": {
            "title": "Compatible con",
            "content": "<p><a href=\"\/products\/delta-2-portable-power-station\" target=\"_blank\" title=\"Estación de Energía Portátil EcoFlow DELTA 2\">DELTA 2<\/a> <\/p><p><a href=\"\/products\/delta-max-portable-power-station\" target=\"_blank\" title=\"Estación de Energía Portátil EcoFlow DELTA Max\">DELTA Max 2000<\/a><\/p><p><a href=\"https:\/\/www.ecoflow.com\/products\/delta-2-max-portable-power-station\" target=\"_blank\" title=\"https:\/\/www.ecoflow.com\/products\/delta-2-max-portable-power-station\">DELTA 2 Max<\/a><\/p>"
          }
        }
      },
      "block_order": [
        "3d0793c4-e505-4afc-8f59-75b81df8f0f7",
        "afbf26f2-d811-42b6-8440-3a4487013c3f",
        "29870530-ec9f-4290-853a-0f44c74f270e",
        "19377af7-ebea-42a5-914c-c1cd31d8e1ea",
        "26e9c21f-90cc-4504-8415-ec2795cc27bc",
        "aedd994c-83a4-47e7-912a-11067e096dff",
        "c4d514e9-ce85-4c2a-a69d-d7dfb16f8748",
        "bdaee37a-1d07-4d2d-8003-1c0738a60517"
      ],
      "settings": {
        "section_id": "",
        "title": "Especificaciones"
      }
    },
    "17141204686a4c89ae": {
      "type": "apps",
      "settings": {
        "include_margins": false
      }
    }
  },
  "order": [
    "sticky-product-bar",
    "main",
    "product-recommendations",
    "f3e56056-c27e-472e-b3ee-3a70d6306c68",
    "0fa0c5cf-3f3f-4a49-8697-c4e2c14793fa",
    "c2d6654e-c56d-4556-8857-709667908743",
    "17141204686a4c89ae"
  ]
}
